sc_retail_email_sender/__init__.py
sc_retail_email_sender/exceptions.py
sc_retail_email_sender/main.py
sc_retail_email_sender/utils.py
sc_retail_email_sender/configs/__init__.py
sc_retail_email_sender/configs/default.py
sc_retail_email_sender/email/__init__.py
sc_retail_email_sender/email/email_sender.py
sc_retail_email_sender/tests/__init__.py
sc_retail_email_sender/tests/email_tests.py
sc_retail_email_sender/tests/sample_config/email-template.html
sc_retail_email_sender/tests/sample_config/production-detail.yml
sc_retail_email_sender/tests/sample_config/production.yml
sc_retail_email_sender-0.0.1.dist-info/LICENSE
sc_retail_email_sender-0.0.1.dist-info/METADATA
sc_retail_email_sender-0.0.1.dist-info/WHEEL
sc_retail_email_sender-0.0.1.dist-info/entry_points.txt
sc_retail_email_sender-0.0.1.dist-info/top_level.txt
sc_retail_email_sender-0.0.1.dist-info/RECORD
